Lab09/Part 1/ALU.v
`define AND   4'b0000
`define OR    4'b0001
`define ADD   4'b0010
`define SUB   4'b0110
`define PassB 4'b0111
`define LSL   4'b0011
`define LSR   4'b0100


module ALU(BusW, BusA, BusB, ALUCtrl, Zero);
    
    parameter n = 64;

    output  [n-1:0] BusW;
    input   [n-1:0] BusA, BusB;
    input   [3:0] ALUCtrl;
    output  Zero;
    
    reg     [n-1:0] BusW;
    
    always @(ALUCtrl or BusA or BusB) begin
        case(ALUCtrl)
            `AND: begin
                BusW <= #20 BusA & BusB;
             end
            `OR: begin
                BusW <= #20 BusA | BusB;
             end
            `ADD: begin
                BusW <= #20 BusA + BusB;
             end
            `SUB: begin
                BusW <= #20 BusA - BusB;
             end
            `PassB: begin
                BusW <= #20 BusB;
             end
            `LSL: begin
                BusW <= #20 BusA << BusB;
             end
            `LSR: begin
                BusW <= #20 BusA << BusB;
             end

        endcase
    end
	
    reg other;
    assign #1 Zero = other;
    
    always @(BusW) begin
      if(BusW==0)begin
        other = 1'b1;
      end
      else begin
        other = 1'b0;
      end
    end
    
    
endmodule

Lab09/Part 2/DataMemory.v
`define SIZE 1024

module DataMemory(ReadData , Address , WriteData , MemoryRead , MemoryWrite , Clock);
    input [63:0]      WriteData;
    input [63:0]      Address;
    input             Clock, MemoryRead, MemoryWrite;
    output reg [63:0] ReadData;

    reg [7:0]         memBank [`SIZE-1:0];


    // This task is used to write arbitrary data to the Data Memory by
    // the intialization block.
    task initset;
      input [63:0] addr;
      input [63:0] data;
      begin
     memBank[addr] =  data[63:56] ; // Big-endian for the win...
     memBank[addr+1] =  data[55:48];
     memBank[addr+2] =  data[47:40];
     memBank[addr+3] =  data[39:32];
     memBank[addr+4] =  data[31:24];
     memBank[addr+5] =  data[23:16];
     memBank[addr+6] =  data[15:8];
     memBank[addr+7] =  data[7:0];
      end
    endtask


    initial
    begin
        // preseting some data in the data memory used by test #1

        // Address 0x0 gets 0x1
        initset( 64'h0,  64'h1);  //Counter variable
        initset( 64'h8,  64'ha);  //Part of mask
        initset( 64'h10, 64'h5);  //Other part of mask
        initset( 64'h18, 64'h0ffbea7deadbeeff); //big constant
        initset( 64'h20, 64'h0); //clearing space

        // Add any data you need for your tests here.

    end

    // This always block reads the data memory and places a double word
    // on the ReadData bus.
    always @(posedge Clock)
    begin
        if(MemoryRead)
        begin
            ReadData[63:56] <= #20 memBank[Address];
            ReadData[55:48] <= #20 memBank[Address+1];
            ReadData[47:40] <= #20 memBank[Address+2];
            ReadData[39:32] <= #20 memBank[Address+3];
            ReadData[31:24] <= #20 memBank[Address+4];
            ReadData[23:16] <= #20 memBank[Address+5];
            ReadData[15:8] <= #20 memBank[Address+6];
            ReadData[7:0] <= #20 memBank[Address+7];
        end
    end

    // This always block takes data from the WriteData bus and writes
    // it into the DataMemory.
    always @(posedge Clock)
    begin
        if(MemoryWrite)
        begin
            memBank[Address] <= #20 WriteData[63:56] ;
            memBank[Address+1] <= #20 WriteData[55:48];
            memBank[Address+2] <= #20 WriteData[47:40];
            memBank[Address+3] <= #20 WriteData[39:32];
            memBank[Address+4] <= #20 WriteData[31:24];
            memBank[Address+5] <= #20 WriteData[23:16];
            memBank[Address+6] <= #20 WriteData[15:8];
            memBank[Address+7] <= #20 WriteData[7:0];
            // Could be useful for debugging:
            $display("Writing Address:%h Data:%h",Address, WriteData);
        end
    end
endmodule

Lab09/Part 1/SignExtender.v
module SignExtender(BusImm, Imm26, Ctrl);
	output reg [63:0] BusImm;
	input [25:0] Imm26;
  	input [1:0] Ctrl;
	
  
  	always@(*)
	  begin
	    if(Ctrl == 2'b00)
	      begin
		BusImm [63:0] = {{52{Imm26[21]}},Imm26[21:10]}; //i type
	      end
	    if(Ctrl == 2'b01)
	      begin
		BusImm [63:0] = {{55{Imm26[20]}},Imm26[20:12]}; //d type
	      end
	    if(Ctrl == 2'b10)
	      begin
		BusImm [63:0] = {{38{Imm26[25]}},Imm26[25:0]}; //b type
	      end
	    if(Ctrl == 2'b11)
	      begin
		BusImm [63:0] = {{45{Imm26[23]}},Imm26[23:5]}; //cb type
	      end

	end
endmodule

Lab09/Part 1/NextPCLogic.v
module NextPClogic(NextPC, CurrentPC, SignExtImm64, Branch, ALUZero, Uncondbranch);
      	input [63:0] CurrentPC, SignExtImm64; 
      	input Branch, ALUZero, Uncondbranch; 
      	output reg [63:0] NextPC; 
        reg [63:0] temp;

       always@ (*)	
        begin
          temp = SignExtImm64 << 2;
          if(Uncondbranch | (Branch & ALUZero))				
           	NextPC = #3 CurrentPC + temp;							
          else
           	NextPC = #2 CurrentPC + 4;									
        end
endmodule

Lab09/Part 1/RegisterFile.v
module RegisterFile(BusA, BusB, BusW, RA, RB, RW, RegWr, Clk);
    output [63:0] BusA;
    output [63:0] BusB;
    input [63:0] BusW;
    input [4:0] RW, RA, RB;
    input RegWr;
    input Clk;
    
    
    reg [63:0] registers [31:0];
    
    initial begin
        registers[31] = 0;
    end
     
    assign #2 BusA = registers[RA];
    assign #2 BusB = registers[RB];
     
    always @ (negedge Clk) 
      begin
        if(RegWr)
            if(RegWr != 31)
                registers[RW] <= #3 BusW;
            registers[31] <= #3 0;
      end
endmodule

Lab09/Part 1/SingleCycleControl.v
`define OPCODE_ANDREG 11'b?0001010???
`define OPCODE_ORRREG 11'b?0101010???
`define OPCODE_ADDREG 11'b?0?01011???
`define OPCODE_SUBREG 11'b?1?01011???

`define OPCODE_ADDIMM 11'b?0?10001???
`define OPCODE_SUBIMM 11'b?1?10001???

`define OPCODE_MOVZ   11'b110100101??

`define OPCODE_B      11'b?00101?????
`define OPCODE_CBZ    11'b?011010????

`define OPCODE_LDUR   11'b??111000010
`define OPCODE_STUR   11'b??111000000

module control(
    output reg reg2loc,
    output reg alusrc,
    output reg mem2reg,
    output reg regwrite,
    output reg memread,
    output reg memwrite,
    output reg branch,
    output reg uncond_branch,
    output reg [3:0] aluop,
    output reg [1:0] signop,
    input [10:0] opcode
);

always @(*)
begin
    casez (opcode)
    
    `OPCODE_ANDREG : 
	begin // AND
	    reg2loc       <= 1'b0;
            alusrc        <= 1'b0;
            mem2reg       <= 1'b0;
            regwrite      <= 1'b1;
            memread       <= 1'b0;
            memwrite      <= 1'b0;
            branch        <= 1'b0;
            uncond_branch <= 1'b0;
            aluop         <= 4'b0000;
            signop        <= 2'bxx;
	end
		
    `OPCODE_ORRREG : // ORR
	begin
	    reg2loc       <= 1'b0;
            alusrc        <= 1'b0;
            mem2reg       <= 1'b0;
            regwrite      <= 1'b1;
            memread       <= 1'b0;
            memwrite      <= 1'b0;
            branch        <= 1'b0;
            uncond_branch <= 1'b0;
            aluop         <= 4'b0001;
            signop        <= 2'bxx;
	end
		
    `OPCODE_ADDREG : // ADDR
	begin
	    reg2loc       <= 1'b0;
            alusrc        <= 1'b0;
            mem2reg       <= 1'b0;
            regwrite      <= 1'b1;
            memread       <= 1'b0;
            memwrite      <= 1'b0;
            branch        <= 1'b0;
            uncond_branch <= 1'b0;
            aluop         <= 4'b0010;
            signop        <= 2'bxx;
	end
		
    `OPCODE_SUBREG : // SUBR
	begin
	    reg2loc       <= 1'b0;
            alusrc        <= 1'b0;
            mem2reg       <= 1'b0;
            regwrite      <= 1'b1;
            memread       <= 1'b0;
            memwrite      <= 1'b0;
            branch        <= 1'b0;
            uncond_branch <= 1'b0;
            aluop         <= 4'b0110;
            signop        <= 2'bxx;
        end
		
    `OPCODE_ADDIMM : // ADDI			
	begin
	    reg2loc       <= 1'bx;
            alusrc        <= 1'b1;
            mem2reg       <= 1'b0;
            regwrite      <= 1'b1;
            memread       <= 1'b0;
            memwrite      <= 1'b0;
            branch        <= 1'b0;
            uncond_branch <= 1'b0;
            aluop         <= 4'b0010;
            signop        <= 2'b00;
		end
		
    `OPCODE_SUBIMM : // SUBI			
	begin
	    reg2loc       <= 1'bx;
            alusrc        <= 1'b1;
            mem2reg       <= 1'b0;
            regwrite      <= 1'b1;
            memread       <= 1'b0;
            memwrite      <= 1'b0;
            branch        <= 1'b0;
            uncond_branch <= 1'b0;
            aluop         <= 4'b0110;
            signop        <= 2'b00;
	end
		
		
    `OPCODE_B : // B
	begin
	    reg2loc       <= 1'bx;
            alusrc        <= 1'b0;
            mem2reg       <= 1'bx;
            regwrite      <= 1'b0;
            memread       <= 1'b0;
            memwrite      <= 1'b0;
            branch        <= 1'b0;
            uncond_branch <= 1'b1;
            aluop         <= 4'b0111;
            signop        <= 2'b10;
	end
		
    `OPCODE_CBZ : // CBZ
	begin
	    reg2loc       <= 1'b1;
            alusrc        <= 1'b0;
            mem2reg       <= 1'bx;
            regwrite      <= 1'b0;
            memread       <= 1'b0;
            memwrite      <= 1'b0;
            branch        <= 1'b1;
            uncond_branch <= 1'b0;
            aluop         <= 4'b0111;
            signop        <= 2'b11;
	end
		
    `OPCODE_LDUR : // LDUR
	  begin
	    reg2loc       <= 1'bx;
            alusrc        <= 1'b1;
            mem2reg       <= 1'b1;
            regwrite      <= 1'b1;
            memread       <= 1'b1;
            memwrite      <= 1'b0;
            branch        <= 1'b0;
            uncond_branch <= 1'b0;
            aluop         <= 4'b0010;
            signop        <= 2'b01;
	  end
		
    `OPCODE_STUR : //STUR
	  begin
	    reg2loc       <= 1'b1;
            alusrc        <= 1'b1;
            mem2reg       <= 1'bx;
            regwrite      <= 1'b0;
            memread       <= 1'b0;
            memwrite      <= 1'b1;
            branch        <= 1'b0;
            uncond_branch <= 1'b0;
            aluop         <= 4'b0010;
            signop        <= 2'b01;
	  end

        default:
        begin
            reg2loc       <= 1'bx;
            alusrc        <= 1'bx;
            mem2reg       <= 1'bx;
            regwrite      <= 1'b0;
            memread       <= 1'b0;
            memwrite      <= 1'b0;
            branch        <= 1'b0;
            uncond_branch <= 1'b0;
            aluop         <= 4'bxxxx;
            signop        <= 2'bxx;
        end
    endcase
end

endmodule

Lab09/Part 1/InstructionMemory.v
module InstructionMemory(Data, Address);
   parameter T_rd = 20;
   parameter MemSize = 40;
   
   output [31:0] Data;
   input [63:0]  Address;
   reg [31:0] 	 Data;
   
   /*
    * ECEN 350 Processor Test Functions
    * Texas A&M University
    */
   
   always @ (Address) begin
      case(Address)

	/* Test Program 1:
	 * Program loads constants from the data memory. Uses these constants to test
	 * the following instructions: LDUR, ORR, AND, CBZ, ADD, SUB, STUR and B.
	 * 
	 * Assembly code for test:
	 * 
	 * 0: LDUR X9, [XZR, 0x0]    //Load 1 into x9
	 * 4: LDUR X10, [XZR, 0x8]   //Load a into x10
	 * 8: LDUR X11, [XZR, 0x10]  //Load 5 into x11
	 * C: LDUR X12, [XZR, 0x18]  //Load big constant into x12
	 * 10: LDUR X13, [XZR, 0x20]  //load a 0 into X13
	 * 
	 * 14: ORR X10, X10, X11  //Create mask of 0xf
	 * 18: AND X12, X12, X10  //Mask off low order bits of big constant
	 * 
	 * loop:
	 * 1C: CBZ X12, end  //while X12 is not 0
	 * 20: ADD X13, X13, X9  //Increment counter in X13
	 * 24: SUB X12, X12, X9  //Decrement remainder of big constant in X12
	 * 28: B loop  //Repeat till X12 is 0
	 * 2C: STUR X13, [XZR, 0x20]  //store back the counter value into the memory location 0x20
	 */
	

	63'h000: Data = 32'hF84003E9;
	63'h004: Data = 32'hF84083EA;
	63'h008: Data = 32'hF84103EB;
	63'h00c: Data = 32'hF84183EC;
	63'h010: Data = 32'hF84203ED;
	63'h014: Data = 32'hAA0B014A;
	63'h018: Data = 32'h8A0A018C;
	63'h01c: Data = 32'hB400008C;
	63'h020: Data = 32'h8B0901AD;
	63'h024: Data = 32'hCB09018C;
	63'h028: Data = 32'h17FFFFFD;
	63'h02c: Data = 32'hF80203ED;
	63'h030: Data = 32'hF84203ED;  //One last load to place stored value on memdbus for test checking.

	
        
			
	default: Data = 32'hXXXXXXXX;
      endcase
   end
endmodule

Lab09/Part 1/SingleCycleProc.v
`timescale 1ns / 1ps
module singlecycle(
    input resetl,
    input [63:0] startpc,
    output reg [63:0] currentpc,
    output [63:0] dmemout,
    input CLK
);

    // Next PC connections
  wire [63:0] nextpc;     // The next PC, to be updated on clock cycle

    // Instruction Memory connections
  wire [31:0] instruction;  // The current instruction

    // Parts of instruction
    wire [4:0] rd;            // The destination register
    wire [4:0] rm;            // Operand 1
    wire [4:0] rn;            // Operand 2
    wire [10:0] opcode;

    // Control wires
    wire reg2loc;
    wire alusrc;
    wire mem2reg;
    wire regwrite;
    wire memread;
    wire memwrite;
    wire branch;
    wire uncond_branch;
    wire [3:0] aluctrl;
  	wire [1:0] signop;

    // Register file connections
    wire [63:0] regoutA;     // Output A
    wire [63:0] regoutB;     // Output B

    // ALU connections
    wire [63:0] aluout;
        wire [63:0] inputB; 
        assign inputB = alusrc ? extimm : regoutB;
    wire zero;

    wire [63:0] extimm;
	
    wire [63:0] busW;
  	assign busW = mem2reg ? dmemout : aluout;

    // PC update logic
    always @(negedge CLK)
    begin
        if (resetl)
            currentpc <= nextpc;
        else
            currentpc <= startpc;
    end

    // Parts of instruction
    assign rd = instruction[4:0];
    assign rm = instruction[9:5];
    assign rn = reg2loc ? instruction[4:0] : instruction[20:16];
    assign opcode = instruction[31:21];

  
    InstructionMemory imem(
        .Data(instruction),
        .Address(currentpc)
    );
  
  
    control control(
        .reg2loc(reg2loc),
        .alusrc(alusrc),
        .mem2reg(mem2reg),
        .regwrite(regwrite),
        .memread(memread),
        .memwrite(memwrite),
        .branch(branch),
        .uncond_branch(uncond_branch),
        .aluop(aluctrl),
        .signop(signop),
        .opcode(opcode)
    );
  
  
	
    RegisterFile rf(
        .BusA(regoutA),
        .BusB(regoutB),
        .BusW(busW),
        .RA(rm),
        .RB(rn),
        .RW(instruction[4:0]),
        .RegWr(regwrite),
        .Clk(CLK)
    );
	
    NextPClogic npc(
        .NextPC(nextpc),
        .CurrentPC(currentpc),
        .SignExtImm64(extimm),
        .Branch(branch),
        .ALUZero(zero),
        .Uncondbranch(uncond_branch)
    );

    
	SignExtender se(
        .BusImm(extimm),
        .Imm26(instruction[25:0]),
        .Ctrl(signop)
    );
	
    DataMemory dmem(
        .ReadData(dmemout),
        .Address(aluout),
        .WriteData(regoutB),
        .MemoryRead(memread),
        .MemoryWrite(memwrite),
        .Clock(CLK)
    );
	
  	ALU alu(.BusW(aluout),
       .BusA(regoutA),
       .BusB(inputB),
       .ALUCtrl(aluctrl),
       .Zero(zero)
    );
  
  
	

	
endmodule

Lab09/Part 1/SingleCycleProcTest.v
`timescale 1ns / 1ps

`include "ALU.v"
`include "DataMemory.v"
`include "InstructionMemory.v"
`include "NextPCLogic.v"
`include "RegisterFile.v"
`include "SignExtender.v"
`include "SingleCycleControl.v"


`define STRLEN 32
`define HalfClockPeriod 60
`define ClockPeriod `HalfClockPeriod * 2

module SingleCycleProcTest_v;

    initial
    begin
        $dumpfile("singlecycle.vcd");
        $dumpvars;
    end

    // These tasks are used to check if a given test has passed and
    // confirm that all tests passed.
    task passTest;
        input [63:0] actualOut, expectedOut;
        input [`STRLEN*8:0] testType;
        inout [7:0] 	  passed;

        if(actualOut == expectedOut) begin $display ("%s passed", testType); passed = passed + 1; end
        else $display ("%s failed: 0x%x should be 0x%x", testType, actualOut, expectedOut);
    endtask

    task allPassed;
        input [7:0] passed;
        input [7:0] numTests;

        if(passed == numTests) $display ("All tests passed");
        else $display("Some tests failed: %d of %d passed", passed, numTests);
    endtask

    // Inputs
    reg        CLK;
    reg        Reset_L;
    reg [63:0] startPC;
    reg [7:0]  passed;
    reg [15:0] watchdog;

    // Outputs
    wire [63:0] dMemOut;
    wire [63:0] currentPC;

    // Instantiate the Unit Under Test (UUT)
    singlecycle uut (
        .CLK(CLK),
        .resetl(Reset_L),
        .startpc(startPC),
        .currentpc(currentPC),
        .dmemout(dMemOut)
    );

    initial begin
        // Initialize Inputs
        Reset_L = 1;
        startPC = 0;
        passed = 0;

        // Initialize Watchdog timer
        watchdog = 0;

        // Wait for global reset
        #(1 * `ClockPeriod);
		
        // Program 1
        #1
        Reset_L = 0; startPC = 0;
        #(1 * `ClockPeriod);
        Reset_L = 1;

        // ***********************************************************
        // This while loop will continue cycling the processor until the
        // PC reaches the final instruction in the first test.  If the
        // program forms an infinite loop, never reaching the end, the
        // watchdog timer will kick in and kill simulation after 64K
        // cycles.
        // ***********************************************************

        while (currentPC < 64'h34)
        begin
           #(1 * `ClockPeriod);
          $display("CurrentPC:%h\ndMemOut:%h",currentPC,dMemOut);
        end
        #(1 * `ClockPeriod);	// One more cycle to load the pass code from the DataMemory.
        passTest(dMemOut, 64'hF, "Results of Program 1", passed);

        // ***********************************************************
        // Add your new tests here
        // ***********************************************************
        
        // Done
        allPassed(passed, 1);   // Be sure to change the one to match
                                // the number of tests you add.
        $finish;
    end

    initial begin
        CLK = 0;
    end

    // The following is correct if clock starts at LOW level at StartTime //
    always begin
        #`HalfClockPeriod CLK = ~CLK;
        #`HalfClockPeriod CLK = ~CLK;
        watchdog = watchdog +1;
    end

    // Kill the simulation if the watchdog hits 64K cycles
    always @*
        if (watchdog == 16'hFF)
        begin
            $display("Watchdog Timer Expired.");
            $finish;
        end


endmodule

Lab09/Part 1/singlecycle.vcd
$date
	Sun Jan 31 16:59:56 2021
$end
$version
	Icarus Verilog
$end
$timescale
	1ps
$end
$scope module SingleCycleProcTest_v $end
$var wire 64 ! dMemOut [63:0] $end
$var wire 64 " currentPC [63:0] $end
$var reg 1 # CLK $end
$var reg 1 $ Reset_L $end
$var reg 8 % passed [7:0] $end
$var reg 64 & startPC [63:0] $end
$var reg 16 ' watchdog [15:0] $end
$scope module uut $end
$var wire 1 # CLK $end
$var wire 1 $ resetl $end
$var wire 64 ( startpc [63:0] $end
$var wire 1 ) zero $end
$var wire 1 * uncond_branch $end
$var wire 2 + signop [1:0] $end
$var wire 5 , rn [4:0] $end
$var wire 5 - rm [4:0] $end
$var wire 1 . regwrite $end
$var wire 64 / regoutB [63:0] $end
$var wire 64 0 regoutA [63:0] $end
$var wire 1 1 reg2loc $end
$var wire 5 2 rd [4:0] $end
$var wire 11 3 opcode [10:0] $end
$var wire 64 4 nextpc [63:0] $end
$var wire 1 5 memwrite $end
$var wire 1 6 memread $end
$var wire 1 7 mem2reg $end
$var wire 32 8 instruction [31:0] $end
$var wire 64 9 inputB [63:0] $end
$var wire 64 : extimm [63:0] $end
$var wire 64 ; dmemout [63:0] $end
$var wire 64 < busW [63:0] $end
$var wire 1 = branch $end
$var wire 1 > alusrc $end
$var wire 64 ? aluout [63:0] $end
$var wire 4 @ aluctrl [3:0] $end
$var reg 64 A currentpc [63:0] $end
$scope module alu $end
$var wire 64 B BusB [63:0] $end
$var wire 1 ) Zero $end
$var wire 64 C BusA [63:0] $end
$var wire 4 D ALUCtrl [3:0] $end
$var reg 64 E BusW [63:0] $end
$var reg 1 F other $end
$upscope $end
$scope module control $end
$var wire 11 G opcode [10:0] $end
$var reg 4 H aluop [3:0] $end
$var reg 1 > alusrc $end
$var reg 1 = branch $end
$var reg 1 7 mem2reg $end
$var reg 1 6 memread $end
$var reg 1 5 memwrite $end
$var reg 1 1 reg2loc $end
$var reg 1 . regwrite $end
$var reg 2 I signop [1:0] $end
$var reg 1 * uncond_branch $end
$upscope $end
$scope module dmem $end
$var wire 64 J Address [63:0] $end
$var wire 1 # Clock $end
$var wire 1 6 MemoryRead $end
$var wire 1 5 MemoryWrite $end
$var wire 64 K WriteData [63:0] $end
$var reg 64 L ReadData [63:0] $end
$scope task initset $end
$var reg 64 M addr [63:0] $end
$var reg 64 N data [63:0] $end
$upscope $end
$upscope $end
$scope module imem $end
$var wire 64 O Address [63:0] $end
$var reg 32 P Data [31:0] $end
$upscope $end
$scope module npc $end
$var wire 1 ) ALUZero $end
$var wire 1 = Branch $end
$var wire 64 Q CurrentPC [63:0] $end
$var wire 1 * Uncondbranch $end
$var wire 64 R SignExtImm64 [63:0] $end
$var reg 64 S NextPC [63:0] $end
$var reg 64 T temp [63:0] $end
$upscope $end
$scope module rf $end
$var wire 64 U BusA [63:0] $end
$var wire 64 V BusB [63:0] $end
$var wire 64 W BusW [63:0] $end
$var wire 1 # Clk $end
$var wire 5 X RA [4:0] $end
$var wire 5 Y RB [4:0] $end
$var wire 5 Z RW [4:0] $end
$var wire 1 . RegWr $end
$upscope $end
$scope module se $end
$var wire 2 [ Ctrl [1:0] $end
$var wire 26 \ Imm26 [25:0] $end
$var reg 64 ] BusImm [63:0] $end
$upscope $end
$upscope $end
$scope task allPassed $end
$var reg 8 ^ numTests [7:0] $end
$var reg 8 _ passed [7:0] $end
$upscope $end
$scope task passTest $end
$var reg 64 ` actualOut [63:0] $end
$var reg 64 a expectedOut [63:0] $end
$var reg 8 b passed [7:0] $end
$var reg 257 c testType [256:0] $end
$upscope $end
$upscope $end
$enddefinitions $end
#0
$dumpvars
bx c
bx b
bx a
bx `
bx _
bx ^
bx ]
bx \
bx [
bx Z
bx Y
bx X
bx W
bx V
bx U
bx T
bx S
bx R
bx Q
bx P
bx O
b0 N
b100000 M
bx L
bx K
bx J
bx I
bx H
bx G
xF
bx E
bx D
bx C
bx B
bx A
bx @
bx ?
x>
x=
bx <
bx ;
bx :
bx 9
bx 8
x7
x6
x5
bx 4
bx 3
bx 2
x1
bx 0
bx /
x.
bx -
bx ,
bx +
x*
x)
b0 (
b0 '
b0 &
b0 %
1$
0#
bx "
bx !
$end
#60000
1#
#120000
b1 '
0#
#121000
0$
#180000
1#
#240000
b0 9
b0 B
b0 :
b0 R
b0 ]
b1 +
b1 I
b1 [
b10 @
b10 D
b10 H
0*
0=
05
16
1.
17
1>
b0x00x ,
b0x00x Y
b10000000000001111101001 \
b1001 Z
b11111000010 3
b11111000010 G
b11111 -
b11111 X
b1001 2
b11111000010000000000001111101001 8
b11111000010000000000001111101001 P
bx00 T
b0 "
b0 A
b0 O
b0 Q
b10 '
0#
#241000
1$
#242000
b0 0
b0 C
b0 U
b100 4
b100 S
#262000
1F
b0 ?
b0 E
b0 J
#263000
b0 T
1)
#300000
1#
#320000
b1 <
b1 W
b1 !
b1 ;
b1 L
#360000
b1000 9
b1000 B
b1000 :
b1000 R
b1000 ]
b0x0x0 ,
b0x0x0 Y
b10000001000001111101010 \
b1010 Z
b1010 2
b11111000010000001000001111101010 8
b11111000010000001000001111101010 P
b100 "
b100 A
b100 O
b100 Q
b11 '
0#
#362000
b1000 4
b1000 S
#380000
0F
b1000 ?
b1000 E
b1000 J
#381000
b100000 T
0)
#420000
1#
#440000
b1010 <
b1010 W
b1010 !
b1010 ;
b1010 L
#480000
b10000 9
b10000 B
b10000 :
b10000 R
b10000 ]
b0x0x1 ,
b0x0x1 Y
b10000010000001111101011 \
b1011 Z
b1011 2
b11111000010000010000001111101011 8
b11111000010000010000001111101011 P
b1000 "
b1000 A
b1000 O
b1000 Q
b100 '
0#
#482000
b1100 4
b1100 S
#500000
b10000 ?
b10000 E
b10000 J
#540000
1#
#560000
b101 <
b101 W
b101 !
b101 ;
b101 L
#600000
b11000 9
b11000 B
b11000 :
b11000 R
b11000 ]
b0xx0x ,
b0xx0x Y
b10000011000001111101100 \
b1100 Z
b1100 2
b11111000010000011000001111101100 8
b11111000010000011000001111101100 P
b1000000 T
b1100 "
b1100 A
b1100 O
b1100 Q
b101 '
0#
#602000
b10000 4
b10000 S
#620000
b11000 ?
b11000 E
b11000 J
#660000
1#
#680000
b111111111011111010100111110111101010110110111110111011111111 <
b111111111011111010100111110111101010110110111110111011111111 W
b111111111011111010100111110111101010110110111110111011111111 !
b111111111011111010100111110111101010110110111110111011111111 ;
b111111111011111010100111110111101010110110111110111011111111 L
#720000
b100000 9
b100000 B
b100000 :
b100000 R
b100000 ]
b0xxxx ,
b0xxxx Y
b10000100000001111101101 \
b1101 Z
b1101 2
b11111000010000100000001111101101 8
b11111000010000100000001111101101 P
b1100000 T
b10000 "
b10000 A
b10000 O
b10000 Q
b110 '
0#
#722000
b10100 4
b10100 S
#740000
b100000 ?
b100000 E
b100000 J
#780000
1#
#800000
b0 <
b0 W
b0 !
b0 ;
b0 L
#840000
b100000 <
b100000 W
bx +
bx I
bx [
b1 @
b1 D
b1 H
06
07
0>
01
bx 9
bx B
b10110000 :
b10110000 R
b10110000 ]
b1011 ,
b1011 Y
b10000010110000000101001010 \
b1010 Z
b10101010000 3
b10101010000 G
b1010 -
b1010 X
b1010 2
b10101010000010110000000101001010 8
b10101010000010110000000101001010 P
b10000000 T
b10100 "
b10100 A
b10100 O
b10100 Q
b111 '
0#
#842000
b101 9
b101 B
b101 /
b101 K
b101 V
b1010 0
b1010 C
b1010 U
b11000 4
b11000 S
#860000
bx <
bx W
bx ?
bx E
bx J
#862000
b1111 <
b1111 W
b1111 ?
b1111 E
b1111 J
#900000
1#
#960000
b0 @
b0 D
b0 H
b1010 ,
b1010 Y
b10000010100000000110001100 \
b1100 Z
b10001010000 3
b10001010000 G
b1100 -
b1100 X
b1100 2
b10001010000010100000000110001100 8
b10001010000010100000000110001100 P
b1011000000 T
b11000 "
b11000 A
b11000 O
b11000 Q
b1000 '
0#
#962000
b1010 9
b1010 B
b1010 /
b1010 K
b1010 V
b111111111011111010100111110111101010110110111110111011111111 0
b111111111011111010100111110111101010110110111110111011111111 C
b111111111011111010100111110111101010110110111110111011111111 U
b11100 4
b11100 S
#965000
b1111 9
b1111 B
b1111 /
b1111 K
b1111 V
#980000
1F
b0 <
b0 W
b0 ?
b0 E
b0 J
#981000
1)
#982000
0F
b1010 <
b1010 W
b1010 ?
b1010 E
b1010 J
#983000
0)
#985000
b1111 <
b1111 W
b1111 ?
b1111 E
b1111 J
#1020000
1#
#1080000
b100 :
b100 R
b100 ]
b0xxxx <
b0xxxx W
b11 +
b11 I
b11 [
b111 @
b111 D
b111 H
1=
0.
x7
11
b1100 ,
b1100 Y
b10001100 \
b10110100000 3
b10110100000 G
b100 -
b100 X
b10110100000000000000000010001100 8
b10110100000000000000000010001100 P
b11100 "
b11100 A
b11100 O
b11100 Q
b1001 '
0#
#1082000
b111111111011111010100111110111101010110110111110111011111111 9
b111111111011111010100111110111101010110110111110111011111111 B
b111111111011111010100111110111101010110110111110111011111111 /
b111111111011111010100111110111101010110110111110111011111111 K
b111111111011111010100111110111101010110110111110111011111111 V
bx 0
bx C
bx U
b100000 4
b100000 S
#1085000
b1111 9
b1111 B
b1111 /
b1111 K
b1111 V
#1102000
b0xxxxxxxxx0xxxxx0x0x00xxxxx0xxxx0x0x0xx0xx0xxxxx0xxx0xxxxxxxx <
b0xxxxxxxxx0xxxxx0x0x00xxxxx0xxxx0x0x0xx0xx0xxxxx0xxx0xxxxxxxx W
b111111111011111010100111110111101010110110111110111011111111 ?
b111111111011111010100111110111101010110110111110111011111111 E
b111111111011111010100111110111101010110110111110111011111111 J
#1105000
b0xxxx <
b0xxxx W
b1111 ?
b1111 E
b1111 J
#1140000
1#
#1200000
b1111 <
b1111 W
bx +
bx I
bx [
b10 @
b10 D
b10 H
0=
1.
07
01
b100100000001101 :
b100100000001101 R
b100100000001101 ]
b1001 ,
b1001 Y
b11000010010000000110101101 \
b1101 Z
b10001011000 3
b10001011000 G
b1101 -
b1101 X
b1101 2
b10001011000010010000000110101101 8
b10001011000010010000000110101101 P
b10000 T
b100000 "
b100000 A
b100000 O
b100000 Q
b1010 '
0#
#1202000
b1 9
b1 B
b1 /
b1 K
b1 V
b0 0
b0 C
b0 U
b100100 4
b100100 S
#1220000
bx <
bx W
bx ?
bx E
bx J
#1222000
b1 <
b1 W
b1 ?
b1 E
b1 J
#1260000
1#
#1320000
b110 @
b110 D
b110 H
b11000010010000000110001100 \
b1100 Z
b11001011000 3
b11001011000 G
b1100 -
b1100 X
b1100 2
b11001011000010010000000110001100 8
b11001011000010010000000110001100 P
b10010000000110100 T
b100100 "
b100100 A
b100100 O
b100100 Q
b1011 '
0#
#1322000
b1111 0
b1111 C
b1111 U
b101000 4
b101000 S
#1340000
b1111111111111111111111111111111111111111111111111111111111111111 <
b1111111111111111111111111111111111111111111111111111111111111111 W
b1111111111111111111111111111111111111111111111111111111111111111 ?
b1111111111111111111111111111111111111111111111111111111111111111 E
b1111111111111111111111111111111111111111111111111111111111111111 J
#1342000
b1110 <
b1110 W
b1110 ?
b1110 E
b1110 J
#1380000
1#
#1440000
b1111111111111111111111111111111111111111111111111111111111111101 :
b1111111111111111111111111111111111111111111111111111111111111101 R
b1111111111111111111111111111111111111111111111111111111111111101 ]
b0xxx0 <
b0xxx0 W
b10 +
b10 I
b10 [
b111 @
b111 D
b111 H
1*
0.
x7
x1
b111x1 ,
b111x1 Y
b11111111111111111111111101 \
b11101 Z
b10111111 3
b10111111 G
b11111 -
b11111 X
b11101 2
b10111111111111111111111111101 8
b10111111111111111111111111101 P
b101000 "
b101000 A
b101000 O
b101000 Q
b1100 '
0#
#1442000
bx 9
bx B
bx /
bx K
bx V
b0 0
b0 C
b0 U
b101100 4
b101100 S
#1460000
b0x <
b0x W
b1 ?
b1 E
b1 J
#1462000
bx <
bx W
bx ?
bx E
bx J
#1500000
1#
#1560000
b100000 9
b100000 B
b1 +
b1 I
b1 [
b10 @
b10 D
b10 H
0*
15
1>
11
b100000 :
b100000 R
b100000 ]
b1101 ,
b1101 Y
b100000001111101101 \
b1101 Z
b11111000000 3
b11111000000 G
b1101 2
b11111000000000100000001111101101 8
b11111000000000100000001111101101 P
b1111111111111111111111111111111111111111111111111111111111110100 T
b101100 "
b101100 A
b101100 O
b101100 Q
b1101 '
0#
#1562000
b1 /
b1 K
b1 V
#1563000
b100000 4
b100000 S
#1580000
b0x00000 <
b0x00000 W
b100000 ?
b100000 E
b100000 J
#1620000
1#
