Lab06/Mux21/Mux21.v

module Mux21 ( out , in , sel ) ;
  input [ 1 : 0 ] in ; // 2bit input
  input sel ;
  output out ;
  
  wire S1, S2, S3;  // delcaring the wires
  
  not not1(S1, sel);    // the S1 value is the not of the sel
  
  and and1(S2, in[0], S1); // S2 wire is th and with input 0 and S1
  and and2(S3, in[1], sel);  // the S3 wire is the and with input 1 and sel
  
  or or1(out, S2, S3);  // or with S2 and S3
 
endmodule

Lab06/Mux21/Mux21Test.v
`timescale 1ns / 1ps

////////////////////////////////////////////////////////////////////////////////
// Company: 
// Engineer:
//
// Create Date:   13:59:40 03/02/2009
// Design Name:   Mux21
// Module Name:   E:/350/Lab6/Mux21/Mux21Test.v
// Project Name:  Mux21
// Target Device:  
// Tool versions:  
// Description: 
//
// Verilog Test Fixture created by ISE for module: Mux21
//
// Dependencies:
// 
// Revision:
// Revision 0.01 - File Created
// Additional Comments:
// 
////////////////////////////////////////////////////////////////////////////////

`define STRLEN 15
module Mux21Test();

	task passTest;
		input actualOut, expectedOut;
		input [`STRLEN*8:0] testType;
		inout [7:0] passed;
	
		if(actualOut == expectedOut) begin $display ("%s passed", testType); passed = passed + 1; end
		else $display ("%s failed: %d should be %d", testType, actualOut, expectedOut);
	endtask
	
	task allPassed;
		input [7:0] passed;
		input [7:0] numTests;
		
		if(passed == numTests) $display ("All tests passed");
		else $display("Some tests failed");
	endtask
	
	task stim;
		input [1:0] newIn;
		input newSel;
		output [1:0] setIn;
		output setSel;
		
		begin
			#90;
			setIn = newIn;
			setSel = newSel;
		end
	endtask
	
	// Inputs
	reg [1:0] in;
	reg sel;
	reg [7:0] passed;

	// Outputs
	wire out;

   initial //This initial block used to dump all wire/reg values to dump file
     begin
       $dumpfile("Mux21Test.vcd");
       $dumpvars(0,Mux21Test);
     end
	// Instantiate the Unit Under Test (UUT)
	Mux21 uut (
		.out(out), 
		.in(in), 
		.sel(sel)
	);

	initial begin
		// Initialize Inputs
		in = 0;
		sel = 0;
		passed = 0;
		
		stim(0, 0, in, sel); #10; passTest(out, 0, "Select First 0", passed);
		stim(1, 0, in, sel); #10; passTest(out, 1, "Select First 1", passed);
		stim(2, 0, in, sel); #10; passTest(out, 0, "Select First 2", passed);
		stim(3, 0, in, sel); #10; passTest(out, 1, "Select First 3", passed);
		stim(0, 1, in, sel); #10; passTest(out, 0, "Select Second 0", passed);
		stim(1, 1, in, sel); #10; passTest(out, 0, "Select Second 1", passed);
		stim(2, 1, in, sel); #10; passTest(out, 1, "Select Second 2", passed);
		stim(3, 1, in, sel); #10; passTest(out, 1, "Select Second 3", passed);
		#10;
		
		allPassed(passed, 8);
	end
      
endmodule

Lab06/Mux21/Mux21Test.vcd
$date
	Mon Oct 12 11:52:05 2020
$end
$version
	Icarus Verilog
$end
$timescale
	1ps
$end
$scope module Mux21Test $end
$var wire 1 ! out $end
$var reg 2 " in [1:0] $end
$var reg 8 # passed [7:0] $end
$var reg 1 $ sel $end
$scope module uut $end
$var wire 1 % S1 $end
$var wire 1 & S2 $end
$var wire 1 ' S3 $end
$var wire 2 ( in [1:0] $end
$var wire 1 ! out $end
$var wire 1 $ sel $end
$upscope $end
$scope task allPassed $end
$var reg 8 ) numTests [7:0] $end
$var reg 8 * passed [7:0] $end
$upscope $end
$scope task passTest $end
$var reg 1 + actualOut $end
$var reg 1 , expectedOut $end
$var reg 8 - passed [7:0] $end
$var reg 121 . testType [120:0] $end
$upscope $end
$scope task stim $end
$var reg 2 / newIn [1:0] $end
$var reg 1 0 newSel $end
$var reg 2 1 setIn [1:0] $end
$var reg 1 2 setSel $end
$upscope $end
$upscope $end
$enddefinitions $end
#0
$dumpvars
x2
bx 1
00
b0 /
bx .
bx -
x,
x+
bx *
bx )
b0 (
0'
0&
1%
0$
b0 #
b0 "
0!
$end
#90000
02
b0 1
#100000
b1 /
b1 #
b1 -
b101001101100101011011000110010101100011011101000010000001000110011010010111001001110011011101000010000000110000 .
0,
0+
#190000
1!
1&
b1 "
b1 (
b1 1
#200000
b10 /
b10 #
b10 -
b101001101100101011011000110010101100011011101000010000001000110011010010111001001110011011101000010000000110001 .
1,
1+
#290000
0!
0&
b10 "
b10 (
b10 1
#300000
b11 /
b11 #
b11 -
b101001101100101011011000110010101100011011101000010000001000110011010010111001001110011011101000010000000110010 .
0,
0+
#390000
1!
1&
b11 "
b11 (
b11 1
#400000
10
b0 /
b100 #
b100 -
b101001101100101011011000110010101100011011101000010000001000110011010010111001001110011011101000010000000110011 .
1,
1+
#490000
0!
0&
0%
1$
b0 "
b0 (
12
b0 1
#500000
b1 /
b101 #
b101 -
b10100110110010101101100011001010110001101110100001000000101001101100101011000110110111101101110011001000010000000110000 .
0,
0+
#590000
b1 "
b1 (
b1 1
#600000
b10 /
b110 #
b110 -
b10100110110010101101100011001010110001101110100001000000101001101100101011000110110111101101110011001000010000000110001 .
#690000
1!
1'
b10 "
b10 (
b10 1
#700000
b11 /
b111 #
b111 -
b10100110110010101101100011001010110001101110100001000000101001101100101011000110110111101101110011001000010000000110010 .
1,
1+
#790000
b11 "
b11 (
b11 1
#800000
b1000 #
b1000 -
b10100110110010101101100011001010110001101110100001000000101001101100101011000110110111101101110011001000010000000110011 .
#810000
b1000 )
b1000 *
