Lab08/Q1/NextPClogic.v

module NextPClogic(NextPC, CurrentPC, SignExtImm64, Branch, ALUZero, Uncondbranch); 
       input [63:0] CurrentPC, SignExtImm64; 
       input Branch, ALUZero, Uncondbranch; 
       output reg [63:0] NextPC; 
       
       reg [63:0] temp;
       
       always @(*)
         begin		
           temp = SignExtImm64 << 2; // shift the sign extender by 2 
           if(Uncondbranch | (Branch & ALUZero)) //if the bracnh is taken
	      NextPC <= #3 CurrentPC + temp;  
           else
	      NextPC = #2 CurrentPC + 4; // nextPC value when branch is not taken
         end
       
endmodule

Lab08/Q1/NextPClogicTest.v

`timescale 1ns / 1ps
`define STRLEN 32
module NextPClogicTest();

	task passTest;
		input [63:0] actualOut, expectedOut;
		input [`STRLEN*8:0] testType;
		inout [3:0] passed;
	
		if(actualOut == expectedOut) begin $display ("%s passed", testType); passed = passed + 1; end
		else $display ("%s failed: %x should be %x", testType, actualOut, expectedOut);
	endtask
	
	task allPassed;
		input [3:0] passed;
		input [3:0] numTests;
		
		if(passed == numTests) $display ("All tests passed");
		else $display("Some tests failed");
	endtask

	// Inputs
	reg [63:0] CurrentPC, SignExtImm64;
	reg Branch, ALUZero, Uncondbranch;
	reg [3:0] passed;

	// Outputs
	wire [63:0] NextPC;
	reg [63:0] newNextPC;


   initial //This initial block used to dump all wire/reg values to dump file
     begin
       $dumpfile("NextPClogicTest.vcd");
       $dumpvars(0,NextPClogicTest);
     end
     
	// Instantiate the Unit Under Test (UUT)
	NextPClogic uut (
		.CurrentPC(CurrentPC), 
		.SignExtImm64(SignExtImm64), 
		.Branch(Branch), 
		.ALUZero(ALUZero), 
		.Uncondbranch(Uncondbranch),
		.NextPC(NextPC)
	);

	initial begin
		// Initialize Inputs
		CurrentPC = 0; SignExtImm64 = 0; Branch = 0; ALUZero = 0; Uncondbranch = 0; passed = 0;
		#3;
		
		//test 1
		CurrentPC = 10; SignExtImm64 = 20;
		Branch = 0; ALUZero = 0; Uncondbranch = 1; newNextPC = 90;
		#10; passTest(NextPC, newNextPC, "Test 1", passed);
		
		// test 2
		CurrentPC = 16; SignExtImm64 = 2;
		Branch = 1; ALUZero = 1;  Uncondbranch = 0; newNextPC = 24;
		#10; passTest(NextPC, newNextPC, "Test 2", passed);
		
		//test 3
		CurrentPC = 16; SignExtImm64 = 3;
		Branch = 1; ALUZero = 0; Uncondbranch = 0; newNextPC = 20;
		#10; passTest(NextPC, newNextPC, "Test 3", passed);
		
		//test 4
		CurrentPC = 16; SignExtImm64 = 4;
		Branch = 0; ALUZero = 0; Uncondbranch = 1; newNextPC = 32;
		#10; passTest(NextPC, newNextPC, "Test 4", passed);

		allPassed(passed, 4);
		
	end
      
endmodule

Lab08/Q1/NextPClogicTest.vcd
$date
	Mon Nov  9 11:38:28 2020
$end
$version
	Icarus Verilog
$end
$timescale
	1ps
$end
$scope module NextPClogicTest $end
$var wire 64 ! NextPC [63:0] $end
$var reg 1 " ALUZero $end
$var reg 1 # Branch $end
$var reg 64 $ CurrentPC [63:0] $end
$var reg 64 % SignExtImm64 [63:0] $end
$var reg 1 & Uncondbranch $end
$var reg 64 ' newNextPC [63:0] $end
$var reg 4 ( passed [3:0] $end
$scope module uut $end
$var wire 1 " ALUZero $end
$var wire 1 # Branch $end
$var wire 64 ) CurrentPC [63:0] $end
$var wire 64 * SignExtImm64 [63:0] $end
$var wire 1 & Uncondbranch $end
$var reg 64 + NextPC [63:0] $end
$var reg 64 , temp [63:0] $end
$upscope $end
$scope task allPassed $end
$var reg 4 - numTests [3:0] $end
$var reg 4 . passed [3:0] $end
$upscope $end
$scope task passTest $end
$var reg 64 / actualOut [63:0] $end
$var reg 64 0 expectedOut [63:0] $end
$var reg 4 1 passed [3:0] $end
$var reg 257 2 testType [256:0] $end
$upscope $end
$upscope $end
$enddefinitions $end
#0
$dumpvars
bx 2
bx 1
bx 0
bx /
bx .
bx -
b0 ,
bx +
b0 *
b0 )
b0 (
bx '
0&
b0 %
b0 $
0#
0"
bx !
$end
#2000
b100 !
b100 +
#3000
b1010000 ,
b1011010 '
1&
b10100 %
b10100 *
b1010 $
b1010 )
#6000
b1011010 !
b1011010 +
#13000
b1000 ,
b11000 '
0&
1"
1#
b10 %
b10 *
b10000 $
b10000 )
b1 (
b1 1
b10101000110010101110011011101000010000000110001 2
b1011010 0
b1011010 /
#16000
b11000 !
b11000 +
#23000
b1100 ,
b10100 '
0"
b11 %
b11 *
b10 (
b10 1
b10101000110010101110011011101000010000000110010 2
b11000 0
b11000 /
#25000
b10100 !
b10100 +
#33000
b10000 ,
b100000 '
1&
0#
b100 %
b100 *
b11 (
b11 1
b10101000110010101110011011101000010000000110011 2
b10100 0
b10100 /
#36000
b100000 !
b100000 +
#43000
b100 -
b100 .
b100 (
b100 1
b10101000110010101110011011101000010000000110100 2
b100000 0
b100000 /
