Lab08/Q2/MiniRegisterFile.v
module MiniRegisterFile(BusA, BusB, BusW, RA, RB, RW, RegWr, Clk);
    output [63:0] BusA;
    output [63:0] BusB;
    input [63:0] BusW;
    input [4:0] RW, RA, RB;
    input RegWr;
    input Clk;
    
    
    reg [63:0] registers [31:0];
    
    initial begin
        registers[31] = 0;
    end
     
    assign #2 BusA = registers[RA];
    assign #2 BusB = registers[RB];
     
    always @ (negedge Clk) 
      begin
        if(RegWr)
            if(RegWr != 31)
                registers[RW] <= #3 BusW;
            registers[31] <= #3 0;
      end
endmodule

Lab08/Q2/RegisterFileTest.v
`timescale 1ns / 1ps

`define STRLEN 32
module RegisterFileTest();


	task passTest;
		input [63:0] actualOut, expectedOut;
		input [`STRLEN*8:0] testType;
		inout [7:0] passed;
	
		if(actualOut == expectedOut) begin $display ("%s passed", testType); passed = passed + 1; end
		else $display ("%s failed: %d should be %d", testType, actualOut, expectedOut);
	endtask
	
	task allPassed;
		input [7:0] passed;
		input [7:0] numTests;
		
		if(passed == numTests) $display ("All tests passed");
		else $display("Some tests failed");
	endtask

	// Inputs
	reg [63:0] BusW;
	reg [4:0] RA;
	reg [4:0] RB;
	reg [4:0] RW;
	reg RegWr;
	reg Clk;
	reg [7:0] passed;

	// Outputs
	wire [63:0] BusA;
	wire [63:0] BusB;


   initial //This initial block used to dump all wire/reg values to dump file
     begin
       $dumpfile("RegisterFileTest.vcd");
       $dumpvars(0,RegisterFileTest);
     end
     
     
	// Instantiate the Unit Under Test (UUT)
	MiniRegisterFile uut (
		.BusA(BusA), 
		.BusB(BusB), 
		.BusW(BusW), 
		.RA(RA), 
		.RB(RB), 
		.RW(RW), 
		.RegWr(RegWr), 
		.Clk(Clk)
	);

	initial begin
		// Initialize Inputs
		BusW = 0;
		RA = 0;
		RB = 0;
		RW = 0;
		RegWr = 0;
		Clk = 1;
		passed = 0;
		
		#10;

		// Add stimulus here
		{RA, RB, RW, BusW, RegWr} = {5'd31, 5'd31, 5'd31, 64'h0, 1'b0};
		#10
		passTest(BusA, 64'd0, "Initial $0 Check 1", passed);
		passTest(BusB, 64'd0, "Initial $0 Check 2", passed);
		#10; Clk = 0; #10; Clk = 1;
		
		{RA, RB, RW, BusW, RegWr} = {5'd31, 5'd31, 5'd31, 64'h12345678, 1'b1};
		passTest(BusA, 64'd0, "Initial $0 Check 3", passed);
		passTest(BusB, 64'd0, "Initial $0 Check 4", passed);
		#10; Clk = 0; #10; Clk = 1;
		passTest(BusA, 64'd0, "$0 Stays 0 Check 1", passed);
		passTest(BusB, 64'd0, "$0 Stays 0 Check 2", passed);
		
		{RA, RB, RW, BusW, RegWr} = {5'd0, 5'd0, 5'd0, 64'h0, 1'b1};#10; Clk = 0; #10; Clk = 1;
		{RA, RB, RW, BusW, RegWr} = {5'd0, 5'd0, 5'd1, 64'h1, 1'b1};#10; Clk = 0; #10; Clk = 1;
		{RA, RB, RW, BusW, RegWr} = {5'd0, 5'd0, 5'd2, 64'h2, 1'b1};#10; Clk = 0; #10; Clk = 1;
		{RA, RB, RW, BusW, RegWr} = {5'd0, 5'd0, 5'd3, 64'h3, 1'b1};#10; Clk = 0; #10; Clk = 1;
		{RA, RB, RW, BusW, RegWr} = {5'd0, 5'd0, 5'd4, 64'h4, 1'b1};#10; Clk = 0; #10; Clk = 1;
		{RA, RB, RW, BusW, RegWr} = {5'd0, 5'd0, 5'd5, 64'h5, 1'b1};#10; Clk = 0; #10; Clk = 1;
		{RA, RB, RW, BusW, RegWr} = {5'd0, 5'd0, 5'd6, 64'h6, 1'b1};#10; Clk = 0; #10; Clk = 1;
		{RA, RB, RW, BusW, RegWr} = {5'd0, 5'd0, 5'd7, 64'h7, 1'b1};#10; Clk = 0; #10; Clk = 1;
		{RA, RB, RW, BusW, RegWr} = {5'd0, 5'd0, 5'd8, 64'h8, 1'b1};#10; Clk = 0; #10; Clk = 1;
		{RA, RB, RW, BusW, RegWr} = {5'd0, 5'd0, 5'd9, 64'h9, 1'b1};#10; Clk = 0; #10; Clk = 1;
		{RA, RB, RW, BusW, RegWr} = {5'd0, 5'd0, 5'd10, 64'd10, 1'b1};#10; Clk = 0; #10; Clk = 1;
		{RA, RB, RW, BusW, RegWr} = {5'd0, 5'd0, 5'd11, 64'd11, 1'b1};#10; Clk = 0; #10; Clk = 1;
		{RA, RB, RW, BusW, RegWr} = {5'd0, 5'd0, 5'd12, 64'd12, 1'b1};#10; Clk = 0; #10; Clk = 1;
		{RA, RB, RW, BusW, RegWr} = {5'd0, 5'd0, 5'd13, 64'd13, 1'b1};#10; Clk = 0; #10; Clk = 1;
		{RA, RB, RW, BusW, RegWr} = {5'd0, 5'd0, 5'd14, 64'd14, 1'b1};#10; Clk = 0; #10; Clk = 1;
		{RA, RB, RW, BusW, RegWr} = {5'd0, 5'd0, 5'd15, 64'd15, 1'b1};#10; Clk = 0; #10; Clk = 1;
		{RA, RB, RW, BusW, RegWr} = {5'd0, 5'd0, 5'd16, 64'd16, 1'b1};#10; Clk = 0; #10; Clk = 1;
		{RA, RB, RW, BusW, RegWr} = {5'd0, 5'd0, 5'd17, 64'd17, 1'b1};#10; Clk = 0; #10; Clk = 1;
		{RA, RB, RW, BusW, RegWr} = {5'd0, 5'd0, 5'd18, 64'd18, 1'b1};#10; Clk = 0; #10; Clk = 1;
		{RA, RB, RW, BusW, RegWr} = {5'd0, 5'd0, 5'd19, 64'd19, 1'b1};#10; Clk = 0; #10; Clk = 1;
		{RA, RB, RW, BusW, RegWr} = {5'd0, 5'd0, 5'd20, 64'd20, 1'b1};#10; Clk = 0; #10; Clk = 1;
		{RA, RB, RW, BusW, RegWr} = {5'd0, 5'd0, 5'd21, 64'd21, 1'b1};#10; Clk = 0; #10; Clk = 1;
		{RA, RB, RW, BusW, RegWr} = {5'd0, 5'd0, 5'd22, 64'd22, 1'b1};#10; Clk = 0; #10; Clk = 1;
		{RA, RB, RW, BusW, RegWr} = {5'd0, 5'd0, 5'd23, 64'd23, 1'b1};#10; Clk = 0; #10; Clk = 1;
		{RA, RB, RW, BusW, RegWr} = {5'd0, 5'd0, 5'd24, 64'd24, 1'b1};#10; Clk = 0; #10; Clk = 1;
		{RA, RB, RW, BusW, RegWr} = {5'd0, 5'd0, 5'd25, 64'd25, 1'b1};#10; Clk = 0; #10; Clk = 1;
		{RA, RB, RW, BusW, RegWr} = {5'd0, 5'd0, 5'd26, 64'd26, 1'b1};#10; Clk = 0; #10; Clk = 1;
		{RA, RB, RW, BusW, RegWr} = {5'd0, 5'd0, 5'd27, 64'd27, 1'b1};#10; Clk = 0; #10; Clk = 1;
		{RA, RB, RW, BusW, RegWr} = {5'd0, 5'd0, 5'd28, 64'd28, 1'b1};#10; Clk = 0; #10; Clk = 1;
		{RA, RB, RW, BusW, RegWr} = {5'd0, 5'd0, 5'd29, 64'd29, 1'b1};#10; Clk = 0; #10; Clk = 1;
		{RA, RB, RW, BusW, RegWr} = {5'd0, 5'd0, 5'd30, 64'd30, 1'b1};#10; Clk = 0; #10; Clk = 1;
		{RA, RB, RW, BusW, RegWr} = {5'd0, 5'd0, 5'd31, 64'd31, 1'b1};#10; Clk = 0; #10; Clk = 1;

		{RA, RB, RW, BusW, RegWr} = {5'd1, 5'd2, 5'd1, 64'h12345678, 1'b1};
		#4;
		passTest(BusA, 64'd1, "Initial Value Check 1", passed);
		passTest(BusB, 64'd2, "Initial Value Check 2", passed);
		#6; Clk = 0; #10; Clk = 1;
		passTest(BusA, 64'h12345678, "Value Updated 1", passed);
		passTest(BusB, 64'd2, "Value Stayed Same 1", passed);

		{RA, RB, RW, BusW, RegWr} = {5'd3, 5'd4, 5'd3, 64'h12345678, 1'b0};
		#4;
		passTest(BusA, 64'd3, "Initial Value Check 3", passed);
		passTest(BusB, 64'd4, "Initial Value Check 4", passed);
		#6; Clk = 0; #10; Clk = 1;
		passTest(BusA, 64'd3, "Value Not Updated 2", passed);
		passTest(BusB, 64'd4, "Value Stayed Same 2", passed);
		
		{RA, RB, RW, BusW, RegWr} = {5'd5, 5'd6, 5'd3, 64'h12345678, 1'b0};
		#4;
		passTest(BusA, 64'd5, "Initial Value Check 5", passed);
		passTest(BusB, 64'd6, "Initial Value Check 6", passed);
		#6; Clk = 0; #10; Clk = 1;
		passTest(BusA, 64'd5, "Value Not Updated 3", passed);
		passTest(BusB, 64'd6, "Value Stayed Same 3", passed);
		
		{RA, RB, RW, BusW, RegWr} = {5'd7, 5'd8, 5'd3, 64'h12345678, 1'b0};
		#4;
		passTest(BusA, 64'd7, "Initial Value Check 7", passed);
		passTest(BusB, 64'd8, "Initial Value Check 8", passed);
		#6; Clk = 0; #10; Clk = 1;
		passTest(BusA, 64'd7, "Value Not Updated 4", passed);
		passTest(BusB, 64'd8, "Value Stayed Same 4", passed);
		
		{RA, RB, RW, BusW, RegWr} = {5'd9, 5'd10, 5'd3, 64'h12345678, 1'b0};
		#4;
		passTest(BusA, 64'd9, "Initial Value Check 9", passed);
		passTest(BusB, 64'd10, "Initial Value Check 10", passed);
		#6; Clk = 0; #10; Clk = 1;
		passTest(BusA, 64'd9, "Value Not Updated 5", passed);
		passTest(BusB, 64'd10, "Value Stayed Same 5", passed);

		{RA, RB, RW, BusW, RegWr} = {5'd11, 5'd12, 5'd3, 64'h12345678, 1'b0};
		#4;
		passTest(BusA, 64'd11, "Initial Value Check 11", passed);
		passTest(BusB, 64'd12, "Initial Value Check 12", passed);
		#6; Clk = 0; #10; Clk = 1;
		passTest(BusA, 64'd11, "Value Not Updated 6", passed);
		passTest(BusB, 64'd12, "Value Stayed Same 6", passed);

		{RA, RB, RW, BusW, RegWr} = {5'd13, 5'd14, 5'd3, 64'h12345678, 1'b0};
		#4;
		passTest(BusA, 64'd13, "Initial Value Check 13", passed);
		passTest(BusB, 64'd14, "Initial Value Check 14", passed);
		#6; Clk = 0; #10; Clk = 1;
		passTest(BusA, 64'd13, "Value Not Updated 7", passed);
		passTest(BusB, 64'd14, "Value Stayed Same 7", passed);

		{RA, RB, RW, BusW, RegWr} = {5'd15, 5'd16, 5'd3, 64'h12345678, 1'b0};
		#4;
		passTest(BusA, 64'd15, "Initial Value Check 15", passed);
		passTest(BusB, 64'd16, "Initial Value Check 16", passed);
		#6; Clk = 0; #10; Clk = 1;
		passTest(BusA, 64'd15, "Value Not Updated 8", passed);
		passTest(BusB, 64'd16, "Value Stayed Same 8", passed);

		{RA, RB, RW, BusW, RegWr} = {5'd17, 5'd18, 5'd3, 64'h12345678, 1'b0};
		#4;
		passTest(BusA, 64'd17, "Initial Value Check 17", passed);
		passTest(BusB, 64'd18, "Initial Value Check 18", passed);
		#6; Clk = 0; #10; Clk = 1;
		passTest(BusA, 64'd17, "Value Not Updated 9", passed);
		passTest(BusB, 64'd18, "Value Stayed Same 9", passed);

		{RA, RB, RW, BusW, RegWr} = {5'd19, 5'd20, 5'd3, 64'h12345678, 1'b0};
		#4;
		passTest(BusA, 64'd19, "Initial Value Check 19", passed);
		passTest(BusB, 64'd20, "Initial Value Check 20", passed);
		#6; Clk = 0; #10; Clk = 1;
		passTest(BusA, 64'd19, "Value Not Updated 10", passed);
		passTest(BusB, 64'd20, "Value Stayed Same 10", passed);

		{RA, RB, RW, BusW, RegWr} = {5'd21, 5'd22, 5'd3, 64'h12345678, 1'b0};
		#4;
		passTest(BusA, 64'd21, "Initial Value Check 21", passed);
		passTest(BusB, 64'd22, "Initial Value Check 22", passed);
		#6; Clk = 0; #10; Clk = 1;
		passTest(BusA, 64'd21, "Value Not Updated 11", passed);
		passTest(BusB, 64'd22, "Value Stayed Same 11", passed);

		{RA, RB, RW, BusW, RegWr} = {5'd23, 5'd24, 5'd3, 64'h12345678, 1'b0};
		#4;
		passTest(BusA, 64'd23, "Initial Value Check 23", passed);
		passTest(BusB, 64'd24, "Initial Value Check 24", passed);
		#6; Clk = 0; #10; Clk = 1;
		passTest(BusA, 64'd23, "Value Not Updated 12", passed);
		passTest(BusB, 64'd24, "Value Stayed Same 12", passed);

		{RA, RB, RW, BusW, RegWr} = {5'd25, 5'd26, 5'd3, 64'h12345678, 1'b0};
		#4;
		passTest(BusA, 64'd25, "Initial Value Check 25", passed);
		passTest(BusB, 64'd26, "Initial Value Check 26", passed);
		#6; Clk = 0; #10; Clk = 1;
		passTest(BusA, 64'd25, "Value Not Updated 13", passed);
		passTest(BusB, 64'd26, "Value Stayed Same 13", passed);

		{RA, RB, RW, BusW, RegWr} = {5'd27, 5'd28, 5'd3, 64'h12345678, 1'b0};
		#4;
		passTest(BusA, 64'd27, "Initial Value Check 27", passed);
		passTest(BusB, 64'd28, "Initial Value Check 28", passed);
		#6; Clk = 0; #10; Clk = 1;
		passTest(BusA, 64'd27, "Value Not Updated 14", passed);
		passTest(BusB, 64'd28, "Value Stayed Same 14", passed);

		{RA, RB, RW, BusW, RegWr} = {5'd29, 5'd30, 5'd3, 64'h12345678, 1'b0};
		#4;
		passTest(BusA, 64'd29, "Initial Value Check 29", passed);
		passTest(BusB, 64'd30, "Initial Value Check 30", passed);
		#6; Clk = 0; #10; Clk = 1;
		passTest(BusA, 64'd29, "Value Not Updated 15", passed);
		passTest(BusB, 64'd30, "Value Stayed Same 15", passed);

		{RA, RB, RW, BusW, RegWr} = {5'd31, 5'd31, 5'd3, 64'h12345678, 1'b0};
		#4;
		passTest(BusA, 64'd0, "Initial Value Check 31", passed);
		#6; Clk = 0; #10; Clk = 1;
		passTest(BusA, 64'd0, "Value Not Updated 16", passed);

		allPassed(passed, 68);
	end
      
endmodule

Lab08/Q2/RegisterFileTest2.vcd
$date
	Mon Nov  9 11:47:04 2020
$end
$version
	Icarus Verilog
$end
$timescale
	1ps
$end
$scope module RegisterFileTest $end
$var wire 64 ! BusB [63:0] $end
$var wire 64 " BusA [63:0] $end
$var reg 64 # BusW [63:0] $end
$var reg 1 $ Clk $end
$var reg 5 % RA [4:0] $end
$var reg 5 & RB [4:0] $end
$var reg 5 ' RW [4:0] $end
$var reg 1 ( RegWr $end
$var reg 8 ) passed [7:0] $end
$scope module uut $end
$var wire 64 * BusA [63:0] $end
$var wire 64 + BusB [63:0] $end
$var wire 64 , BusW [63:0] $end
$var wire 1 $ Clk $end
$var wire 5 - RA [4:0] $end
$var wire 5 . RB [4:0] $end
$var wire 5 / RW [4:0] $end
$var wire 1 ( RegWr $end
$upscope $end
$scope task allPassed $end
$var reg 8 0 numTests [7:0] $end
$var reg 8 1 passed [7:0] $end
$upscope $end
$scope task passTest $end
$var reg 64 2 actualOut [63:0] $end
$var reg 64 3 expectedOut [63:0] $end
$var reg 8 4 passed [7:0] $end
$var reg 257 5 testType [256:0] $end
$upscope $end
$upscope $end
$enddefinitions $end
#0
$dumpvars
bx 5
bx 4
bx 3
bx 2
bx 1
bx 0
b0 /
b0 .
b0 -
b0 ,
bx +
bx *
b0 )
0(
b0 '
b0 &
b0 %
1$
b0 #
bx "
bx !
$end
#10000
1(
#20000
0$
#25000
b0 "
b0 *
b0 !
b0 +
#30000
b1 '
b1 /
b1 #
b1 ,
1$
#40000
0$
#50000
b10 '
b10 /
b10 #
b10 ,
1$
#60000
0$
#70000
b11 '
b11 /
b11 #
b11 ,
1$
#80000
0$
#90000
b100 '
b100 /
b100 #
b100 ,
1$
#100000
0$
#110000
b101 '
b101 /
b101 #
b101 ,
1$
#120000
0$
#130000
b110 '
b110 /
b110 #
b110 ,
1$
#140000
0$
#150000
b111 '
b111 /
b111 #
b111 ,
1$
#160000
0$
#170000
b1000 '
b1000 /
b1000 #
b1000 ,
1$
#180000
0$
#190000
b1001 '
b1001 /
b1001 #
b1001 ,
1$
#200000
0$
#210000
b1010 '
b1010 /
b1010 #
b1010 ,
1$
#220000
0$
#230000
b1011 '
b1011 /
b1011 #
b1011 ,
1$
#240000
0$
#250000
b1100 '
b1100 /
b1100 #
b1100 ,
1$
#260000
0$
#270000
b1101 '
b1101 /
b1101 #
b1101 ,
1$
#280000
0$
#290000
b1110 '
b1110 /
b1110 #
b1110 ,
1$
#300000
0$
#310000
b1111 '
b1111 /
b1111 #
b1111 ,
1$
#320000
0$
#330000
b10000 '
b10000 /
b10000 #
b10000 ,
1$
#340000
0$
#350000
b10001 '
b10001 /
b10001 #
b10001 ,
1$
#360000
0$
#370000
b10010 '
b10010 /
b10010 #
b10010 ,
1$
#380000
0$
#390000
b10011 '
b10011 /
b10011 #
b10011 ,
1$
#400000
0$
#410000
b10100 '
b10100 /
b10100 #
b10100 ,
1$
#420000
0$
#430000
b10101 '
b10101 /
b10101 #
b10101 ,
1$
#440000
0$
#450000
b10110 '
b10110 /
b10110 #
b10110 ,
1$
#460000
0$
#470000
b10111 '
b10111 /
b10111 #
b10111 ,
1$
#480000
0$
#490000
b11000 '
b11000 /
b11000 #
b11000 ,
1$
#500000
0$
#510000
b11001 '
b11001 /
b11001 #
b11001 ,
1$
#520000
0$
#530000
b11010 '
b11010 /
b11010 #
b11010 ,
1$
#540000
0$
#550000
b11011 '
b11011 /
b11011 #
b11011 ,
1$
#560000
0$
#570000
b11100 '
b11100 /
b11100 #
b11100 ,
1$
#580000
0$
#590000
b11101 '
b11101 /
b11101 #
b11101 ,
1$
#600000
0$
#610000
b11110 '
b11110 /
b11110 #
b11110 ,
1$
#620000
0$
#630000
b11111 '
b11111 /
b11111 #
b11111 ,
1$
#640000
0$
#650000
b1 &
b1 .
b0 '
b0 /
b0 #
b0 ,
0(
1$
#652000
b1 !
b1 +
#654000
b10 )
b10 4
b10000100111010101110011010000100010000001000011011010000110010101100011011010110010000000110001001000000101100000110001 5
b1 3
b1 2
#660000
0$
#670000
b10 %
b10 -
b11 &
b11 .
b1 '
b1 /
b1000000000000 #
b1000000000000 ,
b100 )
b100 4
b10000100111010101110011010000100010000001000011011010000110010101100011011010110010000000110010001000000101100000110001 5
b1 3
b1 2
1$
#672000
b10 "
b10 *
b11 !
b11 +
#674000
b110 )
b110 4
b10000100111010101110011010000100010000001000011011010000110010101100011011010110010000000110001001000000101100000110011 5
b11 3
b11 2
#680000
0$
#690000
b100 %
b100 -
b101 &
b101 .
1(
b1000 )
b1000 4
b10000100111010101110011010000100010000001000011011010000110010101100011011010110010000000110010001000000101100000110011 5
b11 3
b11 2
1$
#692000
b100 "
b100 *
b101 !
b101 +
#694000
b1010 )
b1010 4
b10000100111010101110011010000100010000001000011011010000110010101100011011010110010000000110001001000000101100000110101 5
b101 3
b101 2
#700000
0$
#710000
b110 %
b110 -
b111 &
b111 .
b1010 '
b1010 /
b1000000010000 #
b1000000010000 ,
b1100 )
b1100 4
b10000100111010101110011010000100010000001000011011010000110010101100011011010110010000000110010001000000101100000110101 5
b101 3
b101 2
1$
#712000
b110 "
b110 *
b111 !
b111 +
#714000
b1110 )
b1110 4
b10000100111010101110011010000100010000001000011011010000110010101100011011010110010000000110001001000000101100000110111 5
b111 3
b111 2
#720000
0$
#730000
b1000 %
b1000 -
b1001 &
b1001 .
b1011 '
b1011 /
b100000011000000000000 #
b100000011000000000000 ,
b10000 )
b10000 4
b10000100111010101110011010000100010000001000011011010000110010101100011011010110010000000110010001000000101100000110111 5
b111 3
b111 2
1$
#732000
b1000 "
b1000 *
b1001 !
b1001 +
#734000
b10010 )
b10010 4
b100001001110101011100110100001000100000010000110110100001100101011000110110101100100000001100010010000000111001 5
b1001 3
b1001 2
#740000
0$
#750000
b1010 %
b1010 -
b1011 &
b1011 .
b1100 '
b1100 /
b0 #
b0 ,
0(
b10100 )
b10100 4
b10000100111010101110011010000100010000001000011011010000110010101100011011010110010000000110010001000000101100000111001 5
b1001 3
b1001 2
1$
#752000
b1000000010000 "
b1000000010000 *
b100000011000000000000 !
b100000011000000000000 +
#754000
b10110 )
b10110 4
b1000010011101010111001101000010001000000100001101101000011001010110001101101011001000000011000100100000010110000011000100110001 5
b100000011000000000000 3
b100000011000000000000 2
#760000
0$
#770000
b1100 %
b1100 -
b1101 &
b1101 .
b1101 '
b1101 /
b1010101111001101 #
b1010101111001101 ,
1(
b11000 )
b11000 4
b1000010011101010111001101000010001000000100001101101000011001010110001101101011001000000011001000100000010110000011000100110001 5
b100000011000000000000 3
b100000011000000000000 2
1$
#772000
b1100 "
b1100 *
b1101 !
b1101 +
#774000
b11010 )
b11010 4
b1000010011101010111001101000010001000000100001101101000011001010110001101101011001000000011000100100000010110000011000100110011 5
b1101 3
b1101 2
#780000
0$
#785000
b1010101111001101 !
b1010101111001101 +
#790000
b1110 %
b1110 -
b1111 &
b1111 .
b1110 '
b1110 /
b1001000010000000000000001001 #
b1001000010000000000000001001 ,
0(
b11100 )
b11100 4
b1000010011101010111001101000010001000000100001101101000011001010110001101101011001000000011001000100000010110000011000100110011 5
b1010101111001101 3
b1010101111001101 2
1$
#792000
b1110 "
b1110 *
b1111 !
b1111 +
#794000
b11110 )
b11110 4
b1000010011101010111001101000010001000000100001101101000011001010110001101101011001000000011000100100000010110000011000100110101 5
b1111 3
b1111 2
#800000
0$
#810000
b100000 0
b100000 1
b100000 )
b100000 4
b1000010011101010111001101000010001000000100001101101000011001010110001101101011001000000011001000100000010110000011000100110101 5
b1111 3
b1111 2
1$
